scclip/__init__.py
scclip/callback.py
scclip/clip.py
scclip/config.py
scclip/data.py
scclip/lightning.py
scclip/logger.py
scclip/metrics.py
scclip/model.py
scclip/plot.py
scclip/vit.py
scclip-0.0.1.dist-info/METADATA
scclip-0.0.1.dist-info/WHEEL
scclip-0.0.1.dist-info/top_level.txt
scclip-0.0.1.dist-info/RECORD
