Metadata-Version: 2.1
Name: scclip
Version: 0.0.1
License: MIT
Classifier: Development Status :: 4 - Beta
Classifier: Intended Audience :: Science/Research
Classifier: License :: OSI Approved :: MIT License
Classifier: Programming Language :: Python :: 3.7
Classifier: Operating System :: MacOS :: MacOS X
Classifier: Operating System :: Microsoft :: Windows
Classifier: Operating System :: POSIX :: Linux
Classifier: Topic :: Scientific/Engineering :: Bio-Informatics
Requires-Python: >3.6.0
Requires-Dist: numpy >=1.22.1
Requires-Dist: pandas >=1.4.0
Requires-Dist: scipy >=1.7.3
Requires-Dist: torch >=1.10.0
Requires-Dist: pytorch-lightning <2.0
Requires-Dist: lightning <2.0
Requires-Dist: scanpy >=1.8.2
Requires-Dist: muon >=0.1.2
Requires-Dist: leidenalg >=0.8.3
Requires-Dist: einops >=0.6
Requires-Dist: colorcet >=3.0.1
Requires-Dist: transformers
Requires-Dist: pre-commit >=3.4.0
